wooldridge/__init__.py
wooldridge/load_data.py
wooldridge/datasets/401k.csv.bz2
wooldridge/datasets/401ksubs.csv.bz2
wooldridge/datasets/__init__.py
wooldridge/datasets/admnrev.csv.bz2
wooldridge/datasets/affairs.csv.bz2
wooldridge/datasets/airfare.csv.bz2
wooldridge/datasets/alcohol.csv.bz2
wooldridge/datasets/apple.csv.bz2
wooldridge/datasets/approval.csv.bz2
wooldridge/datasets/athlet1.csv.bz2
wooldridge/datasets/athlet2.csv.bz2
wooldridge/datasets/attend.csv.bz2
wooldridge/datasets/audit.csv.bz2
wooldridge/datasets/barium.csv.bz2
wooldridge/datasets/beauty.csv.bz2
wooldridge/datasets/benefits.csv.bz2
wooldridge/datasets/beveridge.csv.bz2
wooldridge/datasets/big9salary.csv.bz2
wooldridge/datasets/bwght.csv.bz2
wooldridge/datasets/bwght2.csv.bz2
wooldridge/datasets/campus.csv.bz2
wooldridge/datasets/card.csv.bz2
wooldridge/datasets/catholic.csv.bz2
wooldridge/datasets/cement.csv.bz2
wooldridge/datasets/census2000.csv.bz2
wooldridge/datasets/ceosal1.csv.bz2
wooldridge/datasets/ceosal2.csv.bz2
wooldridge/datasets/charity.csv.bz2
wooldridge/datasets/consump.csv.bz2
wooldridge/datasets/corn.csv.bz2
wooldridge/datasets/countymurders.csv.bz2
wooldridge/datasets/cps78_85.csv.bz2
wooldridge/datasets/cps91.csv.bz2
wooldridge/datasets/crime1.csv.bz2
wooldridge/datasets/crime2.csv.bz2
wooldridge/datasets/crime3.csv.bz2
wooldridge/datasets/crime4.csv.bz2
wooldridge/datasets/discrim.csv.bz2
wooldridge/datasets/driving.csv.bz2
wooldridge/datasets/earns.csv.bz2
wooldridge/datasets/econmath.csv.bz2
wooldridge/datasets/elem94_95.csv.bz2
wooldridge/datasets/engin.csv.bz2
wooldridge/datasets/expendshares.csv.bz2
wooldridge/datasets/ezanders.csv.bz2
wooldridge/datasets/ezunem.csv.bz2
wooldridge/datasets/fair.csv.bz2
wooldridge/datasets/fertil1.csv.bz2
wooldridge/datasets/fertil2.csv.bz2
wooldridge/datasets/fertil3.csv.bz2
wooldridge/datasets/fish.csv.bz2
wooldridge/datasets/fringe.csv.bz2
wooldridge/datasets/gpa1.csv.bz2
wooldridge/datasets/gpa2.csv.bz2
wooldridge-0.5.0.dist-info/licenses/LICENSE
wooldridge-0.5.0.dist-info/METADATA
wooldridge-0.5.0.dist-info/WHEEL
wooldridge-0.5.0.dist-info/top_level.txt
wooldridge-0.5.0.dist-info/RECORD
