Metadata-Version: 2.4
Name: wooldridge
Version: 0.5.0
Summary: Data sets from Introductory Econometrics: A Modern Approach (7th ed, J.M. Wooldridge)
Home-page: https://github.com/spring-haru/wooldridge
Author: Tetsu Haruyama
Author-email: tetsu.yes@gmail.com
License: LICENSE
Keywords: data,wooldridge,econometrics
License-File: LICENSE
Requires-Dist: pandas
Dynamic: author
Dynamic: author-email
Dynamic: description
Dynamic: description-content-type
Dynamic: home-page
Dynamic: keywords
Dynamic: license
Dynamic: license-file
Dynamic: requires-dist
Dynamic: summary
